shellcraft/__init__.py
shellcraft/_cli_impl.py
shellcraft/_colors.py
shellcraft/automata.py
shellcraft/cli.py
shellcraft/core.py
shellcraft/data/events.toml
shellcraft/data/fractions.toml
shellcraft/data/game_state.proto
shellcraft/data/guild_names.grammar
shellcraft/data/letter.grammar
shellcraft/data/missions.toml
shellcraft/data/names.grammar
shellcraft/data/research.toml
shellcraft/data/tools.toml
shellcraft/data/tutorials.toml
shellcraft/epithets.py
shellcraft/events.py
shellcraft/exceptions.py
shellcraft/fractions.py
shellcraft/game_state_pb2.py
shellcraft/grammar.py
shellcraft/missions.py
shellcraft/research.py
shellcraft/shellcraft.py
shellcraft/tools.py
shellcraft/tutorial.py
shellcraft/utils.py
shellcraft/world.py
shellcraft-0.12.0.dist-info/entry_points.txt
shellcraft-0.12.0.dist-info/LICENSE
shellcraft-0.12.0.dist-info/WHEEL
shellcraft-0.12.0.dist-info/METADATA
shellcraft-0.12.0.dist-info/RECORD
