Metadata-Version: 2.1
Name: shellcraft
Version: 0.12.0
Summary: ShellCraft is a command line based crafting game.
Home-page: https://maebert.github.io/shellcraft
License: MIT
Author: Manuel Ebert
Author-email: manuel@1450.me
Requires-Python: >=3.6,<4.0
Classifier: License :: OSI Approved :: MIT License
Classifier: Programming Language :: Python :: 3
Classifier: Programming Language :: Python :: 3.6
Classifier: Programming Language :: Python :: 3.7
Classifier: Programming Language :: Python :: 3.8
Requires-Dist: click (>=7.0,<8.0)
Requires-Dist: protobuf (>=3.8,<4.0)
Requires-Dist: toml (>=0.10.2,<0.11.0)
Project-URL: Changelog, https://github.com/maebert/shellcraft/releases
Project-URL: Repository, https://github.com/maebert/shellcraft
